<?xml version="1.0" encoding="utf-8"?>
<TextureAtlas imagePath="aceCrazy.png">
	<!-- Created with Adobe Animate version 21.0.7.42652 -->
	<!-- http://www.adobe.com/products/animate.html -->
	<SubTexture name="AceCutscene0000" x="0" y="0" width="0" height="0" frameX="167" frameY="143" frameWidth="666" frameHeight="159"/>
	<SubTexture name="AceCutscene0001" x="0" y="0" width="0" height="0" frameX="167" frameY="143" frameWidth="666" frameHeight="159"/>
	<SubTexture name="AceCutscene0002" x="0" y="0" width="0" height="0" frameX="167" frameY="143" frameWidth="666" frameHeight="159"/>
	<SubTexture name="AceCutscene0003" x="0" y="0" width="0" height="0" frameX="167" frameY="143" frameWidth="666" frameHeight="159"/>
	<SubTexture name="AceCutscene0004" x="0" y="0" width="0" height="0" frameX="167" frameY="143" frameWidth="666" frameHeight="159"/>
	<SubTexture name="AceCutscene0005" x="0" y="0" width="0" height="0" frameX="167" frameY="143" frameWidth="666" frameHeight="159"/>
	<SubTexture name="AceCutscene0006" x="0" y="0" width="0" height="0" frameX="167" frameY="143" frameWidth="666" frameHeight="159"/>
	<SubTexture name="AceCutscene0007" x="0" y="0" width="0" height="0" frameX="167" frameY="143" frameWidth="666" frameHeight="159"/>
	<SubTexture name="AceCutscene0008" x="0" y="0" width="0" height="0" frameX="167" frameY="143" frameWidth="666" frameHeight="159"/>
	<SubTexture name="AceCutscene0009" x="0" y="0" width="221" height="153" frameX="-9" frameY="-5" frameWidth="666" frameHeight="159"/>
	<SubTexture name="AceCutscene0010" x="221" y="0" width="261" height="151" frameX="0" frameY="-4" frameWidth="666" frameHeight="159"/>
	<SubTexture name="AceCutscene0011" x="482" y="0" width="215" height="154" frameX="-36" frameY="0" frameWidth="666" frameHeight="159"/>
	<SubTexture name="AceCutscene0012" x="697" y="0" width="214" height="155" frameX="-45" frameY="0" frameWidth="666" frameHeight="159"/>
	<SubTexture name="AceCutscene0013" x="0" y="155" width="211" height="155" frameX="-55" frameY="0" frameWidth="666" frameHeight="159"/>
	<SubTexture name="AceCutscene0014" x="211" y="155" width="209" height="156" frameX="-65" frameY="0" frameWidth="666" frameHeight="159"/>
	<SubTexture name="AceCutscene0015" x="420" y="155" width="206" height="155" frameX="-75" frameY="-1" frameWidth="666" frameHeight="159"/>
	<SubTexture name="AceCutscene0016" x="626" y="155" width="204" height="156" frameX="-85" frameY="-1" frameWidth="666" frameHeight="159"/>
	<SubTexture name="AceCutscene0017" x="0" y="311" width="201" height="156" frameX="-95" frameY="-1" frameWidth="666" frameHeight="159"/>
	<SubTexture name="AceCutscene0018" x="201" y="311" width="199" height="157" frameX="-105" frameY="-1" frameWidth="666" frameHeight="159"/>
	<SubTexture name="AceCutscene0019" x="400" y="311" width="196" height="158" frameX="-115" frameY="-1" frameWidth="666" frameHeight="159"/>
	<SubTexture name="AceCutscene0020" x="596" y="311" width="219" height="153" frameX="-111" frameY="-5" frameWidth="666" frameHeight="159"/>
	<SubTexture name="AceCutscene0021" x="0" y="469" width="232" height="151" frameX="-190" frameY="-4" frameWidth="666" frameHeight="159"/>
	<SubTexture name="AceCutscene0022" x="232" y="469" width="215" height="154" frameX="-286" frameY="0" frameWidth="666" frameHeight="159"/>
	<SubTexture name="AceCutscene0023" x="232" y="469" width="215" height="154" frameX="-286" frameY="0" frameWidth="666" frameHeight="159"/>
	<SubTexture name="AceCutscene0024" x="232" y="469" width="215" height="154" frameX="-286" frameY="0" frameWidth="666" frameHeight="159"/>
	<SubTexture name="AceCutscene0025" x="232" y="469" width="215" height="154" frameX="-286" frameY="0" frameWidth="666" frameHeight="159"/>
	<SubTexture name="AceCutscene0026" x="447" y="469" width="180" height="147" frameX="-383" frameY="-8" frameWidth="666" frameHeight="159"/>
	<SubTexture name="AceCutscene0027" x="627" y="469" width="178" height="149" frameX="-438" frameY="-7" frameWidth="666" frameHeight="159"/>
	<SubTexture name="AceCutscene0028" x="805" y="469" width="176" height="150" frameX="-490" frameY="-7" frameWidth="666" frameHeight="159"/>
	<SubTexture name="AceCutscene0029" x="805" y="469" width="176" height="150" frameX="-490" frameY="-7" frameWidth="666" frameHeight="159"/>
	<SubTexture name="AceCutscene0030" x="805" y="469" width="176" height="150" frameX="-490" frameY="-7" frameWidth="666" frameHeight="159"/>
	<SubTexture name="AceCutscene0031" x="805" y="469" width="176" height="150" frameX="-490" frameY="-7" frameWidth="666" frameHeight="159"/>
	<SubTexture name="AceCutscene0032" x="805" y="469" width="176" height="150" frameX="-490" frameY="-7" frameWidth="666" frameHeight="159"/>
	<SubTexture name="AceCutscene0033" x="805" y="469" width="176" height="150" frameX="-490" frameY="-7" frameWidth="666" frameHeight="159"/>
	<SubTexture name="AceCutscene0034" x="805" y="469" width="176" height="150" frameX="-490" frameY="-7" frameWidth="666" frameHeight="159"/>
	<SubTexture name="AceCutscene0035" x="805" y="469" width="176" height="150" frameX="-490" frameY="-7" frameWidth="666" frameHeight="159"/>
	<SubTexture name="AceCutscene0036" x="805" y="469" width="176" height="150" frameX="-490" frameY="-7" frameWidth="666" frameHeight="159"/>
	<SubTexture name="AceCutscene0037" x="805" y="469" width="176" height="150" frameX="-490" frameY="-7" frameWidth="666" frameHeight="159"/>
	<SubTexture name="AceCutscene0038" x="805" y="469" width="176" height="150" frameX="-490" frameY="-7" frameWidth="666" frameHeight="159"/>
	<SubTexture name="AceCutscene0039" x="805" y="469" width="176" height="150" frameX="-490" frameY="-7" frameWidth="666" frameHeight="159"/>
	<SubTexture name="AceCutscene0040" x="805" y="469" width="176" height="150" frameX="-490" frameY="-7" frameWidth="666" frameHeight="159"/>
	<SubTexture name="AceCutscene0041" x="805" y="469" width="176" height="150" frameX="-490" frameY="-7" frameWidth="666" frameHeight="159"/>
	<SubTexture name="AceCutscene0042" x="805" y="469" width="176" height="150" frameX="-490" frameY="-7" frameWidth="666" frameHeight="159"/>
	<SubTexture name="AceCutscene0043" x="805" y="469" width="176" height="150" frameX="-490" frameY="-7" frameWidth="666" frameHeight="159"/>
	<SubTexture name="AceCutscene0044" x="805" y="469" width="176" height="150" frameX="-490" frameY="-7" frameWidth="666" frameHeight="159"/>
	<SubTexture name="AceCutscene0045" x="805" y="469" width="176" height="150" frameX="-490" frameY="-7" frameWidth="666" frameHeight="159"/>
	<SubTexture name="AceCutscene0046" x="805" y="469" width="176" height="150" frameX="-490" frameY="-7" frameWidth="666" frameHeight="159"/>
	<SubTexture name="AceCutscene0047" x="805" y="469" width="176" height="150" frameX="-490" frameY="-7" frameWidth="666" frameHeight="159"/>
	<SubTexture name="AceCutscene0048" x="805" y="469" width="176" height="150" frameX="-490" frameY="-7" frameWidth="666" frameHeight="159"/>
	<SubTexture name="AceCutscene0049" x="805" y="469" width="176" height="150" frameX="-490" frameY="-7" frameWidth="666" frameHeight="159"/>
</TextureAtlas>
